{
  "$schema": "https://stacklit.dev/schema/v1.json",
  "version": "1",
  "generated_at": "2026-04-10T01:02:08Z",
  "stacklit_version": "dev",
  "merkle_hash": "c1cf8a0f548cd16ef6a0edb985b906515e4b95d92125c3f45ab80a21a2fe78c9",
  "project": {
    "name": "stacklit-express",
    "root": ".",
    "type": "single"
  },
  "tech": {
    "primary_language": "javascript",
    "languages": {
      "javascript": {
        "files": 141,
        "lines": 21346
      }
    },
    "frameworks": [
      "ESLint",
      "Express",
      "GitHub Actions",
      "Redis"
    ]
  },
  "structure": {
    "entrypoints": null,
    "total_files": 141,
    "total_lines": 21346
  },
  "modules": {
    "examples/auth": {
      "purpose": "Authentication and authorization",
      "language": "javascript",
      "files": 1,
      "lines": 134,
      "file_list": [
        "index.js"
      ],
      "activity": "low"
    },
    "examples/content-negotiation": {
      "purpose": "Content-negotiation",
      "language": "javascript",
      "files": 3,
      "lines": 74,
      "file_list": [
        "db.js",
        "index.js",
        "users.js"
      ],
      "activity": "low"
    },
    "examples/cookie-sessions": {
      "purpose": "Cookie-sessions",
      "language": "javascript",
      "files": 1,
      "lines": 25,
      "file_list": [
        "index.js"
      ],
      "activity": "low"
    },
    "examples/cookies": {
      "purpose": "Cookies",
      "language": "javascript",
      "files": 1,
      "lines": 53,
      "file_list": [
        "index.js"
      ],
      "activity": "low"
    },
    "examples/downloads": {
      "purpose": "Downloads",
      "language": "javascript",
      "files": 1,
      "lines": 40,
      "file_list": [
        "index.js"
      ],
      "activity": "low"
    },
    "examples/ejs": {
      "purpose": "Ejs",
      "language": "javascript",
      "files": 1,
      "lines": 57,
      "file_list": [
        "index.js"
      ],
      "activity": "low"
    },
    "examples/error": {
      "purpose": "Error",
      "language": "javascript",
      "files": 1,
      "lines": 53,
      "file_list": [
        "index.js"
      ],
      "activity": "low"
    },
    "examples/error-pages": {
      "purpose": "Error-pages",
      "language": "javascript",
      "files": 1,
      "lines": 103,
      "file_list": [
        "index.js"
      ],
      "activity": "low"
    },
    "examples/hello-world": {
      "purpose": "Hello-world",
      "language": "javascript",
      "files": 1,
      "lines": 15,
      "file_list": [
        "index.js"
      ],
      "activity": "low"
    },
    "examples/markdown": {
      "purpose": "Markdown",
      "language": "javascript",
      "files": 1,
      "lines": 44,
      "file_list": [
        "index.js"
      ],
      "activity": "low"
    },
    "examples/multi-router": {
      "purpose": "Multi-router",
      "language": "javascript",
      "files": 1,
      "lines": 18,
      "file_list": [
        "index.js"
      ],
      "activity": "low"
    },
    "examples/multi-router/controllers": {
      "purpose": "Controllers",
      "language": "javascript",
      "files": 2,
      "lines": 30,
      "file_list": [
        "api_v1.js",
        "api_v2.js"
      ],
      "activity": "low"
    },
    "examples/mvc": {
      "purpose": "Mvc",
      "language": "javascript",
      "files": 2,
      "lines": 111,
      "file_list": [
        "db.js",
        "index.js"
      ],
      "depends_on": [
        "examples/mvc/lib"
      ],
      "depended_by": [
        "examples/mvc/controllers/pet",
        "examples/mvc/controllers/user",
        "examples/mvc/controllers/user-pet"
      ],
      "activity": "low"
    },
    "examples/mvc/controllers/main": {
      "purpose": "Main",
      "language": "javascript",
      "files": 1,
      "lines": 5,
      "file_list": [
        "index.js"
      ],
      "activity": "low"
    },
    "examples/mvc/controllers/pet": {
      "purpose": "Pet",
      "language": "javascript",
      "files": 1,
      "lines": 31,
      "file_list": [
        "index.js"
      ],
      "depends_on": [
        "examples/mvc"
      ],
      "activity": "low"
    },
    "examples/mvc/controllers/user": {
      "purpose": "User",
      "language": "javascript",
      "files": 1,
      "lines": 41,
      "file_list": [
        "index.js"
      ],
      "depends_on": [
        "examples/mvc"
      ],
      "activity": "low"
    },
    "examples/mvc/controllers/user-pet": {
      "purpose": "User-pet",
      "language": "javascript",
      "files": 1,
      "lines": 22,
      "file_list": [
        "index.js"
      ],
      "depends_on": [
        "examples/mvc"
      ],
      "activity": "low"
    },
    "examples/mvc/lib": {
      "purpose": "Shared library code",
      "language": "javascript",
      "files": 1,
      "lines": 83,
      "file_list": [
        "boot.js"
      ],
      "depended_by": [
        "examples/mvc"
      ],
      "activity": "low"
    },
    "examples/online": {
      "purpose": "Online",
      "language": "javascript",
      "files": 1,
      "lines": 61,
      "file_list": [
        "index.js"
      ],
      "activity": "low"
    },
    "examples/params": {
      "purpose": "Params",
      "language": "javascript",
      "files": 1,
      "lines": 74,
      "file_list": [
        "index.js"
      ],
      "activity": "low"
    },
    "examples/resource": {
      "purpose": "Resource",
      "language": "javascript",
      "files": 1,
      "lines": 95,
      "file_list": [
        "index.js"
      ],
      "activity": "low"
    },
    "examples/route-map": {
      "purpose": "Route-map",
      "language": "javascript",
      "files": 1,
      "lines": 75,
      "file_list": [
        "index.js"
      ],
      "depends_on": [
        "lib"
      ],
      "activity": "low"
    },
    "examples/route-middleware": {
      "purpose": "Route-middleware",
      "language": "javascript",
      "files": 1,
      "lines": 90,
      "file_list": [
        "index.js"
      ],
      "depends_on": [
        "lib"
      ],
      "activity": "low"
    },
    "examples/route-separation": {
      "purpose": "Route-separation",
      "language": "javascript",
      "files": 4,
      "lines": 120,
      "file_list": [
        "index.js",
        "post.js",
        "site.js",
        "user.js"
      ],
      "activity": "low"
    },
    "examples/search": {
      "purpose": "Search",
      "language": "javascript",
      "files": 1,
      "lines": 83,
      "file_list": [
        "index.js"
      ],
      "activity": "low"
    },
    "examples/search/public": {
      "purpose": "Public",
      "language": "javascript",
      "files": 1,
      "lines": 15,
      "file_list": [
        "client.js"
      ],
      "activity": "low"
    },
    "examples/session": {
      "purpose": "Session",
      "language": "javascript",
      "files": 2,
      "lines": 76,
      "file_list": [
        "index.js",
        "redis.js"
      ],
      "activity": "low"
    },
    "examples/static-files": {
      "purpose": "Static-files",
      "language": "javascript",
      "files": 1,
      "lines": 43,
      "file_list": [
        "index.js"
      ],
      "activity": "low"
    },
    "examples/static-files/public/js": {
      "purpose": "Js",
      "language": "javascript",
      "files": 1,
      "lines": 1,
      "file_list": [
        "app.js"
      ],
      "activity": "low"
    },
    "examples/vhost": {
      "purpose": "Vhost",
      "language": "javascript",
      "files": 1,
      "lines": 53,
      "file_list": [
        "index.js"
      ],
      "activity": "low"
    },
    "examples/view-constructor": {
      "purpose": "View-constructor",
      "language": "javascript",
      "files": 2,
      "lines": 101,
      "file_list": [
        "github-view.js",
        "index.js"
      ],
      "activity": "low"
    },
    "examples/view-locals": {
      "purpose": "View-locals",
      "language": "javascript",
      "files": 2,
      "lines": 191,
      "file_list": [
        "index.js",
        "user.js"
      ],
      "activity": "low"
    },
    "examples/web-service": {
      "purpose": "Web-service",
      "language": "javascript",
      "files": 1,
      "lines": 117,
      "file_list": [
        "index.js"
      ],
      "activity": "low"
    },
    "lib": {
      "purpose": "Shared library code",
      "language": "javascript",
      "files": 6,
      "lines": 2762,
      "file_list": [
        "application.js",
        "express.js",
        "request.js",
        "response.js",
        "utils.js",
        "view.js"
      ],
      "depended_by": [
        "examples/route-map",
        "examples/route-middleware",
        "root"
      ],
      "activity": "low"
    },
    "root": {
      "purpose": "Root package",
      "language": "javascript",
      "files": 1,
      "lines": 11,
      "file_list": [
        "index.js"
      ],
      "depends_on": [
        "lib"
      ],
      "activity": "low"
    }
  },
  "dependencies": {
    "edges": [
      [
        "examples/mvc",
        "examples/mvc/lib"
      ],
      [
        "examples/mvc/controllers/pet",
        "examples/mvc"
      ],
      [
        "examples/mvc/controllers/user",
        "examples/mvc"
      ],
      [
        "examples/mvc/controllers/user-pet",
        "examples/mvc"
      ],
      [
        "examples/route-map",
        "lib"
      ],
      [
        "examples/route-middleware",
        "lib"
      ],
      [
        "root",
        "lib"
      ]
    ],
    "entrypoints": null,
    "most_depended": [
      "examples/mvc",
      "lib",
      "examples/mvc/lib",
      "examples/auth",
      "examples/content-negotiation",
      "examples/cookie-sessions",
      "examples/cookies",
      "examples/downloads",
      "examples/ejs",
      "examples/error"
    ],
    "isolated": [
      "examples/auth",
      "examples/content-negotiation",
      "examples/cookie-sessions",
      "examples/cookies",
      "examples/downloads",
      "examples/ejs",
      "examples/error",
      "examples/error-pages",
      "examples/hello-world",
      "examples/markdown",
      "examples/multi-router",
      "examples/multi-router/controllers",
      "examples/mvc/controllers/main",
      "examples/online",
      "examples/params",
      "examples/resource",
      "examples/route-separation",
      "examples/search",
      "examples/search/public",
      "examples/session",
      "examples/static-files",
      "examples/static-files/public/js",
      "examples/vhost",
      "examples/view-constructor",
      "examples/view-locals",
      "examples/web-service"
    ]
  },
  "git": {
    "hot_files": [
      {
        "path": "\"examples/downloads/files/CCTV\\345\\244\\247\\350\\265\\233\\344\\270\\212\\346\\265\\267\\345\\210\\206\\350\\265\\233\\345\\214\\272.txt\"",
        "commits_90d": 1
      },
      {
        "path": "\"test/fixtures/snow \\342\\230\\203/.gitkeep\"",
        "commits_90d": 1
      },
      {
        "path": ".editorconfig",
        "commits_90d": 1
      },
      {
        "path": ".eslintignore",
        "commits_90d": 1
      },
      {
        "path": ".eslintrc.yml",
        "commits_90d": 1
      },
      {
        "path": ".github/dependabot.yml",
        "commits_90d": 1
      },
      {
        "path": ".github/workflows/ci.yml",
        "commits_90d": 1
      },
      {
        "path": ".github/workflows/codeql.yml",
        "commits_90d": 1
      },
      {
        "path": ".github/workflows/legacy.yml",
        "commits_90d": 1
      },
      {
        "path": ".github/workflows/scorecard.yml",
        "commits_90d": 1
      },
      {
        "path": ".gitignore",
        "commits_90d": 1
      },
      {
        "path": ".npmrc",
        "commits_90d": 1
      },
      {
        "path": "History.md",
        "commits_90d": 1
      },
      {
        "path": "LICENSE",
        "commits_90d": 1
      },
      {
        "path": "Readme.md",
        "commits_90d": 1
      },
      {
        "path": "examples/README.md",
        "commits_90d": 1
      },
      {
        "path": "examples/auth/index.js",
        "commits_90d": 1
      },
      {
        "path": "examples/auth/views/foot.ejs",
        "commits_90d": 1
      },
      {
        "path": "examples/auth/views/head.ejs",
        "commits_90d": 1
      },
      {
        "path": "examples/auth/views/login.ejs",
        "commits_90d": 1
      }
    ],
    "recent": [
      ".editorconfig",
      ".eslintignore",
      ".eslintrc.yml",
      ".github/dependabot.yml",
      ".github/workflows/ci.yml",
      ".github/workflows/codeql.yml",
      ".github/workflows/legacy.yml",
      ".github/workflows/scorecard.yml",
      ".gitignore",
      ".npmrc"
    ],
    "stable": [
      "\"examples/downloads/files/CCTV\\345\\244\\247\\350\\265\\233\\344\\270\\212\\346\\265\\267\\345\\210\\206\\350\\265\\233\\345\\214\\272.txt\"",
      "\"test/fixtures/snow \\342\\230\\203/.gitkeep\"",
      ".editorconfig",
      ".eslintignore",
      ".eslintrc.yml",
      ".github/dependabot.yml",
      ".github/workflows/ci.yml",
      ".github/workflows/codeql.yml",
      ".github/workflows/legacy.yml",
      ".github/workflows/scorecard.yml"
    ]
  },
  "hints": {
    "test_command": "npm test",
    "env_vars": [
      "NODE_ENV",
      "NO_DEPRECATION"
    ],
    "do_not_touch": [
      ".github/"
    ]
  },
  "architecture": {}
}